python_package_exercise_17/__init__.py
python_package_exercise_17/simple_wordle.py
python_package_exercise_17/tests.py
3_python_package_exercise_17-0.1.0.dist-info/LICENSE
3_python_package_exercise_17-0.1.0.dist-info/METADATA
3_python_package_exercise_17-0.1.0.dist-info/WHEEL
3_python_package_exercise_17-0.1.0.dist-info/entry_points.txt
3_python_package_exercise_17-0.1.0.dist-info/top_level.txt
3_python_package_exercise_17-0.1.0.dist-info/RECORD
